{
  "country": "KWT",
  "countryName": "Kuwait",
  "sex": "male",
  "year": 2023,
  "source": "UN World Population Prospects 2024",
  "sourceUrl": "https://population.un.org/wpp/",
  "downloadDate": "2026-02-20",
  "entries": [
    {
      "age": 0,
      "qx": 0.007978,
      "lx": 100000,
      "ex": 79.25
    },
    {
      "age": 1,
      "qx": 0.000615,
      "lx": 99202.24,
      "ex": 78.89
    },
    {
      "age": 2,
      "qx": 0.000224,
      "lx": 99141.27,
      "ex": 77.94
    },
    {
      "age": 3,
      "qx": 0.000209,
      "lx": 99119.02,
      "ex": 76.96
    },
    {
      "age": 4,
      "qx": 0.000272,
      "lx": 99098.3,
      "ex": 75.97
    },
    {
      "age": 5,
      "qx": 0.00029,
      "lx": 99071.36,
      "ex": 74.99
    },
    {
      "age": 6,
      "qx": 0.000263,
      "lx": 99042.65,
      "ex": 74.01
    },
    {
      "age": 7,
      "qx": 0.000211,
      "lx": 99016.62,
      "ex": 73.03
    },
    {
      "age": 8,
      "qx": 0.000156,
      "lx": 98995.7,
      "ex": 72.05
    },
    {
      "age": 9,
      "qx": 0.000116,
      "lx": 98980.31,
      "ex": 71.06
    },
    {
      "age": 10,
      "qx": 0.000113,
      "lx": 98968.83,
      "ex": 70.07
    },
    {
      "age": 11,
      "qx": 0.000129,
      "lx": 98957.69,
      "ex": 69.08
    },
    {
      "age": 12,
      "qx": 0.000166,
      "lx": 98944.88,
      "ex": 68.08
    },
    {
      "age": 13,
      "qx": 0.000225,
      "lx": 98928.43,
      "ex": 67.1
    },
    {
      "age": 14,
      "qx": 0.000303,
      "lx": 98906.15,
      "ex": 66.11
    },
    {
      "age": 15,
      "qx": 0.000383,
      "lx": 98876.2,
      "ex": 65.13
    },
    {
      "age": 16,
      "qx": 0.000454,
      "lx": 98838.29,
      "ex": 64.15
    },
    {
      "age": 17,
      "qx": 0.000515,
      "lx": 98793.41,
      "ex": 63.18
    },
    {
      "age": 18,
      "qx": 0.000572,
      "lx": 98742.53,
      "ex": 62.22
    },
    {
      "age": 19,
      "qx": 0.000638,
      "lx": 98686.01,
      "ex": 61.25
    },
    {
      "age": 20,
      "qx": 0.00073,
      "lx": 98623.01,
      "ex": 60.29
    },
    {
      "age": 21,
      "qx": 0.000857,
      "lx": 98551.02,
      "ex": 59.33
    },
    {
      "age": 22,
      "qx": 0.00102,
      "lx": 98466.52,
      "ex": 58.38
    },
    {
      "age": 23,
      "qx": 0.00121,
      "lx": 98366.11,
      "ex": 57.44
    },
    {
      "age": 24,
      "qx": 0.001412,
      "lx": 98247.09,
      "ex": 56.51
    },
    {
      "age": 25,
      "qx": 0.001597,
      "lx": 98108.38,
      "ex": 55.59
    },
    {
      "age": 26,
      "qx": 0.001732,
      "lx": 97951.71,
      "ex": 54.68
    },
    {
      "age": 27,
      "qx": 0.001792,
      "lx": 97782.02,
      "ex": 53.77
    },
    {
      "age": 28,
      "qx": 0.001757,
      "lx": 97606.8,
      "ex": 52.87
    },
    {
      "age": 29,
      "qx": 0.001622,
      "lx": 97435.35,
      "ex": 51.96
    },
    {
      "age": 30,
      "qx": 0.001403,
      "lx": 97277.3,
      "ex": 51.05
    },
    {
      "age": 31,
      "qx": 0.001149,
      "lx": 97140.82,
      "ex": 50.12
    },
    {
      "age": 32,
      "qx": 0.000919,
      "lx": 97029.21,
      "ex": 49.17
    },
    {
      "age": 33,
      "qx": 0.000743,
      "lx": 96940.02,
      "ex": 48.22
    },
    {
      "age": 34,
      "qx": 0.000626,
      "lx": 96868.02,
      "ex": 47.25
    },
    {
      "age": 35,
      "qx": 0.00057,
      "lx": 96807.34,
      "ex": 46.28
    },
    {
      "age": 36,
      "qx": 0.000565,
      "lx": 96752.2,
      "ex": 45.31
    },
    {
      "age": 37,
      "qx": 0.000595,
      "lx": 96697.54,
      "ex": 44.33
    },
    {
      "age": 38,
      "qx": 0.000648,
      "lx": 96639.96,
      "ex": 43.36
    },
    {
      "age": 39,
      "qx": 0.000707,
      "lx": 96577.35,
      "ex": 42.39
    },
    {
      "age": 40,
      "qx": 0.00075,
      "lx": 96509.11,
      "ex": 41.42
    },
    {
      "age": 41,
      "qx": 0.000764,
      "lx": 96436.68,
      "ex": 40.45
    },
    {
      "age": 42,
      "qx": 0.000757,
      "lx": 96362.99,
      "ex": 39.48
    },
    {
      "age": 43,
      "qx": 0.000743,
      "lx": 96290.06,
      "ex": 38.51
    },
    {
      "age": 44,
      "qx": 0.000736,
      "lx": 96218.54,
      "ex": 37.54
    },
    {
      "age": 45,
      "qx": 0.00075,
      "lx": 96147.71,
      "ex": 36.56
    },
    {
      "age": 46,
      "qx": 0.000797,
      "lx": 96075.56,
      "ex": 35.59
    },
    {
      "age": 47,
      "qx": 0.000876,
      "lx": 95999.01,
      "ex": 34.62
    },
    {
      "age": 48,
      "qx": 0.000987,
      "lx": 95914.94,
      "ex": 33.65
    },
    {
      "age": 49,
      "qx": 0.001131,
      "lx": 95820.25,
      "ex": 32.68
    },
    {
      "age": 50,
      "qx": 0.001303,
      "lx": 95711.93,
      "ex": 31.72
    },
    {
      "age": 51,
      "qx": 0.001498,
      "lx": 95587.24,
      "ex": 30.76
    },
    {
      "age": 52,
      "qx": 0.001709,
      "lx": 95444.07,
      "ex": 29.8
    },
    {
      "age": 53,
      "qx": 0.001925,
      "lx": 95281,
      "ex": 28.85
    },
    {
      "age": 54,
      "qx": 0.002133,
      "lx": 95097.57,
      "ex": 27.91
    },
    {
      "age": 55,
      "qx": 0.002312,
      "lx": 94894.76,
      "ex": 26.97
    },
    {
      "age": 56,
      "qx": 0.002447,
      "lx": 94675.34,
      "ex": 26.03
    },
    {
      "age": 57,
      "qx": 0.002545,
      "lx": 94443.71,
      "ex": 25.09
    },
    {
      "age": 58,
      "qx": 0.002628,
      "lx": 94203.38,
      "ex": 24.15
    },
    {
      "age": 59,
      "qx": 0.002725,
      "lx": 93955.78,
      "ex": 23.22
    },
    {
      "age": 60,
      "qx": 0.002864,
      "lx": 93699.79,
      "ex": 22.28
    },
    {
      "age": 61,
      "qx": 0.003081,
      "lx": 93431.43,
      "ex": 21.34
    },
    {
      "age": 62,
      "qx": 0.003399,
      "lx": 93143.55,
      "ex": 20.41
    },
    {
      "age": 63,
      "qx": 0.003838,
      "lx": 92826.95,
      "ex": 19.47
    },
    {
      "age": 64,
      "qx": 0.004428,
      "lx": 92470.69,
      "ex": 18.55
    },
    {
      "age": 65,
      "qx": 0.005211,
      "lx": 92061.25,
      "ex": 17.63
    },
    {
      "age": 66,
      "qx": 0.006243,
      "lx": 91581.56,
      "ex": 16.72
    },
    {
      "age": 67,
      "qx": 0.007595,
      "lx": 91009.82,
      "ex": 15.82
    },
    {
      "age": 68,
      "qx": 0.00935,
      "lx": 90318.64,
      "ex": 14.94
    },
    {
      "age": 69,
      "qx": 0.01161,
      "lx": 89474.18,
      "ex": 14.07
    },
    {
      "age": 70,
      "qx": 0.014493,
      "lx": 88435.38,
      "ex": 13.23
    },
    {
      "age": 71,
      "qx": 0.018126,
      "lx": 87153.69,
      "ex": 12.42
    },
    {
      "age": 72,
      "qx": 0.022614,
      "lx": 85573.95,
      "ex": 11.64
    },
    {
      "age": 73,
      "qx": 0.028004,
      "lx": 83638.77,
      "ex": 10.9
    },
    {
      "age": 74,
      "qx": 0.034248,
      "lx": 81296.57,
      "ex": 10.2
    },
    {
      "age": 75,
      "qx": 0.041163,
      "lx": 78512.3,
      "ex": 9.54
    },
    {
      "age": 76,
      "qx": 0.048397,
      "lx": 75280.47,
      "ex": 8.93
    },
    {
      "age": 77,
      "qx": 0.055682,
      "lx": 71637.1,
      "ex": 8.36
    },
    {
      "age": 78,
      "qx": 0.063016,
      "lx": 67648.2,
      "ex": 7.82
    },
    {
      "age": 79,
      "qx": 0.070527,
      "lx": 63385.27,
      "ex": 7.31
    },
    {
      "age": 80,
      "qx": 0.078471,
      "lx": 58914.92,
      "ex": 6.83
    },
    {
      "age": 81,
      "qx": 0.087248,
      "lx": 54291.8,
      "ex": 6.37
    },
    {
      "age": 82,
      "qx": 0.097183,
      "lx": 49554.96,
      "ex": 5.93
    },
    {
      "age": 83,
      "qx": 0.108366,
      "lx": 44739.06,
      "ex": 5.51
    },
    {
      "age": 84,
      "qx": 0.12085,
      "lx": 39890.87,
      "ex": 5.12
    },
    {
      "age": 85,
      "qx": 0.13466,
      "lx": 35070.07,
      "ex": 4.76
    },
    {
      "age": 86,
      "qx": 0.149784,
      "lx": 30347.55,
      "ex": 4.42
    },
    {
      "age": 87,
      "qx": 0.166104,
      "lx": 25801.98,
      "ex": 4.11
    },
    {
      "age": 88,
      "qx": 0.18332,
      "lx": 21516.16,
      "ex": 3.83
    },
    {
      "age": 89,
      "qx": 0.200993,
      "lx": 17571.82,
      "ex": 3.58
    },
    {
      "age": 90,
      "qx": 0.218555,
      "lx": 14040.01,
      "ex": 3.35
    },
    {
      "age": 91,
      "qx": 0.235318,
      "lx": 10971.49,
      "ex": 3.15
    },
    {
      "age": 92,
      "qx": 0.250886,
      "lx": 8389.7,
      "ex": 2.97
    },
    {
      "age": 93,
      "qx": 0.265789,
      "lx": 6284.84,
      "ex": 2.79
    },
    {
      "age": 94,
      "qx": 0.280868,
      "lx": 4614.4,
      "ex": 2.62
    },
    {
      "age": 95,
      "qx": 0.305243,
      "lx": 3318.36,
      "ex": 2.45
    },
    {
      "age": 96,
      "qx": 0.324662,
      "lx": 2305.45,
      "ex": 2.31
    },
    {
      "age": 97,
      "qx": 0.34414,
      "lx": 1556.96,
      "ex": 2.18
    },
    {
      "age": 98,
      "qx": 0.363544,
      "lx": 1021.15,
      "ex": 2.06
    },
    {
      "age": 99,
      "qx": 0.382744,
      "lx": 649.91,
      "ex": 1.96
    },
    {
      "age": 100,
      "qx": 1,
      "lx": 401.16,
      "ex": 1.86
    }
  ]
}