{
  "country": "SRB",
  "countryName": "Serbia",
  "sex": "male",
  "year": 2023,
  "source": "UN World Population Prospects 2024",
  "sourceUrl": "https://population.un.org/wpp/",
  "downloadDate": "2026-02-20",
  "entries": [
    {
      "age": 0,
      "qx": 0.004602,
      "lx": 100000,
      "ex": 73.5
    },
    {
      "age": 1,
      "qx": 0.000278,
      "lx": 99539.78,
      "ex": 72.84
    },
    {
      "age": 2,
      "qx": 0.000232,
      "lx": 99512.09,
      "ex": 71.86
    },
    {
      "age": 3,
      "qx": 0.0001,
      "lx": 99489,
      "ex": 70.88
    },
    {
      "age": 4,
      "qx": 0.000209,
      "lx": 99479.09,
      "ex": 69.88
    },
    {
      "age": 5,
      "qx": 0.000049,
      "lx": 99458.3,
      "ex": 68.9
    },
    {
      "age": 6,
      "qx": 0.000142,
      "lx": 99453.44,
      "ex": 67.9
    },
    {
      "age": 7,
      "qx": 0.000129,
      "lx": 99439.36,
      "ex": 66.91
    },
    {
      "age": 8,
      "qx": 0.000159,
      "lx": 99426.49,
      "ex": 65.92
    },
    {
      "age": 9,
      "qx": 0.000081,
      "lx": 99410.65,
      "ex": 64.93
    },
    {
      "age": 10,
      "qx": 0.000079,
      "lx": 99402.64,
      "ex": 63.93
    },
    {
      "age": 11,
      "qx": 0.000078,
      "lx": 99394.83,
      "ex": 62.94
    },
    {
      "age": 12,
      "qx": 0.000149,
      "lx": 99387.1,
      "ex": 61.94
    },
    {
      "age": 13,
      "qx": 0.00007,
      "lx": 99372.31,
      "ex": 60.95
    },
    {
      "age": 14,
      "qx": 0.000098,
      "lx": 99365.38,
      "ex": 59.96
    },
    {
      "age": 15,
      "qx": 0.000218,
      "lx": 99355.64,
      "ex": 58.96
    },
    {
      "age": 16,
      "qx": 0.000288,
      "lx": 99333.93,
      "ex": 57.98
    },
    {
      "age": 17,
      "qx": 0.000356,
      "lx": 99305.34,
      "ex": 56.99
    },
    {
      "age": 18,
      "qx": 0.000524,
      "lx": 99269.97,
      "ex": 56.01
    },
    {
      "age": 19,
      "qx": 0.000628,
      "lx": 99217.99,
      "ex": 55.04
    },
    {
      "age": 20,
      "qx": 0.00043,
      "lx": 99155.71,
      "ex": 54.08
    },
    {
      "age": 21,
      "qx": 0.000623,
      "lx": 99113.04,
      "ex": 53.1
    },
    {
      "age": 22,
      "qx": 0.000518,
      "lx": 99051.28,
      "ex": 52.13
    },
    {
      "age": 23,
      "qx": 0.000645,
      "lx": 98999.96,
      "ex": 51.16
    },
    {
      "age": 24,
      "qx": 0.000661,
      "lx": 98936.07,
      "ex": 50.19
    },
    {
      "age": 25,
      "qx": 0.000658,
      "lx": 98870.65,
      "ex": 49.22
    },
    {
      "age": 26,
      "qx": 0.000478,
      "lx": 98805.6,
      "ex": 48.26
    },
    {
      "age": 27,
      "qx": 0.0006,
      "lx": 98758.35,
      "ex": 47.28
    },
    {
      "age": 28,
      "qx": 0.00068,
      "lx": 98699.12,
      "ex": 46.31
    },
    {
      "age": 29,
      "qx": 0.000744,
      "lx": 98631.97,
      "ex": 45.34
    },
    {
      "age": 30,
      "qx": 0.000789,
      "lx": 98558.62,
      "ex": 44.37
    },
    {
      "age": 31,
      "qx": 0.000916,
      "lx": 98480.91,
      "ex": 43.41
    },
    {
      "age": 32,
      "qx": 0.000984,
      "lx": 98390.71,
      "ex": 42.45
    },
    {
      "age": 33,
      "qx": 0.000871,
      "lx": 98293.85,
      "ex": 41.49
    },
    {
      "age": 34,
      "qx": 0.001005,
      "lx": 98208.19,
      "ex": 40.52
    },
    {
      "age": 35,
      "qx": 0.00109,
      "lx": 98109.49,
      "ex": 39.56
    },
    {
      "age": 36,
      "qx": 0.001281,
      "lx": 98002.52,
      "ex": 38.61
    },
    {
      "age": 37,
      "qx": 0.001412,
      "lx": 97876.94,
      "ex": 37.66
    },
    {
      "age": 38,
      "qx": 0.00151,
      "lx": 97738.69,
      "ex": 36.71
    },
    {
      "age": 39,
      "qx": 0.001776,
      "lx": 97591.11,
      "ex": 35.76
    },
    {
      "age": 40,
      "qx": 0.001591,
      "lx": 97417.75,
      "ex": 34.83
    },
    {
      "age": 41,
      "qx": 0.001603,
      "lx": 97262.79,
      "ex": 33.88
    },
    {
      "age": 42,
      "qx": 0.002548,
      "lx": 97106.86,
      "ex": 32.93
    },
    {
      "age": 43,
      "qx": 0.002512,
      "lx": 96859.41,
      "ex": 32.02
    },
    {
      "age": 44,
      "qx": 0.003189,
      "lx": 96616.08,
      "ex": 31.1
    },
    {
      "age": 45,
      "qx": 0.003197,
      "lx": 96308.01,
      "ex": 30.19
    },
    {
      "age": 46,
      "qx": 0.00355,
      "lx": 96000.09,
      "ex": 29.29
    },
    {
      "age": 47,
      "qx": 0.003698,
      "lx": 95659.32,
      "ex": 28.39
    },
    {
      "age": 48,
      "qx": 0.004398,
      "lx": 95305.59,
      "ex": 27.49
    },
    {
      "age": 49,
      "qx": 0.004461,
      "lx": 94886.43,
      "ex": 26.61
    },
    {
      "age": 50,
      "qx": 0.005115,
      "lx": 94463.18,
      "ex": 25.73
    },
    {
      "age": 51,
      "qx": 0.006346,
      "lx": 93979.97,
      "ex": 24.86
    },
    {
      "age": 52,
      "qx": 0.00687,
      "lx": 93383.59,
      "ex": 24.02
    },
    {
      "age": 53,
      "qx": 0.008475,
      "lx": 92742.04,
      "ex": 23.18
    },
    {
      "age": 54,
      "qx": 0.008472,
      "lx": 91956.07,
      "ex": 22.37
    },
    {
      "age": 55,
      "qx": 0.010602,
      "lx": 91177,
      "ex": 21.56
    },
    {
      "age": 56,
      "qx": 0.012095,
      "lx": 90210.38,
      "ex": 20.79
    },
    {
      "age": 57,
      "qx": 0.012978,
      "lx": 89119.27,
      "ex": 20.03
    },
    {
      "age": 58,
      "qx": 0.013784,
      "lx": 87962.66,
      "ex": 19.29
    },
    {
      "age": 59,
      "qx": 0.015991,
      "lx": 86750.18,
      "ex": 18.55
    },
    {
      "age": 60,
      "qx": 0.017112,
      "lx": 85362.98,
      "ex": 17.85
    },
    {
      "age": 61,
      "qx": 0.018832,
      "lx": 83902.23,
      "ex": 17.15
    },
    {
      "age": 62,
      "qx": 0.020424,
      "lx": 82322.23,
      "ex": 16.47
    },
    {
      "age": 63,
      "qx": 0.0217,
      "lx": 80640.88,
      "ex": 15.8
    },
    {
      "age": 64,
      "qx": 0.024773,
      "lx": 78890.94,
      "ex": 15.14
    },
    {
      "age": 65,
      "qx": 0.02428,
      "lx": 76936.55,
      "ex": 14.51
    },
    {
      "age": 66,
      "qx": 0.028623,
      "lx": 75068.51,
      "ex": 13.86
    },
    {
      "age": 67,
      "qx": 0.028862,
      "lx": 72919.78,
      "ex": 13.25
    },
    {
      "age": 68,
      "qx": 0.033458,
      "lx": 70815.18,
      "ex": 12.63
    },
    {
      "age": 69,
      "qx": 0.031997,
      "lx": 68445.82,
      "ex": 12.05
    },
    {
      "age": 70,
      "qx": 0.037736,
      "lx": 66255.79,
      "ex": 11.44
    },
    {
      "age": 71,
      "qx": 0.041411,
      "lx": 63755.57,
      "ex": 10.86
    },
    {
      "age": 72,
      "qx": 0.045418,
      "lx": 61115.41,
      "ex": 10.31
    },
    {
      "age": 73,
      "qx": 0.049784,
      "lx": 58339.66,
      "ex": 9.78
    },
    {
      "age": 74,
      "qx": 0.054534,
      "lx": 55435.27,
      "ex": 9.27
    },
    {
      "age": 75,
      "qx": 0.059696,
      "lx": 52412.13,
      "ex": 8.77
    },
    {
      "age": 76,
      "qx": 0.065297,
      "lx": 49283.32,
      "ex": 8.3
    },
    {
      "age": 77,
      "qx": 0.071364,
      "lx": 46065.28,
      "ex": 7.84
    },
    {
      "age": 78,
      "qx": 0.077925,
      "lx": 42777.87,
      "ex": 7.41
    },
    {
      "age": 79,
      "qx": 0.085008,
      "lx": 39444.39,
      "ex": 6.99
    },
    {
      "age": 80,
      "qx": 0.092639,
      "lx": 36091.29,
      "ex": 6.59
    },
    {
      "age": 81,
      "qx": 0.100841,
      "lx": 32747.84,
      "ex": 6.21
    },
    {
      "age": 82,
      "qx": 0.109638,
      "lx": 29445.51,
      "ex": 5.85
    },
    {
      "age": 83,
      "qx": 0.119048,
      "lx": 26217.18,
      "ex": 5.51
    },
    {
      "age": 84,
      "qx": 0.129088,
      "lx": 23096.07,
      "ex": 5.19
    },
    {
      "age": 85,
      "qx": 0.139769,
      "lx": 20114.64,
      "ex": 4.89
    },
    {
      "age": 86,
      "qx": 0.151097,
      "lx": 17303.23,
      "ex": 4.6
    },
    {
      "age": 87,
      "qx": 0.163071,
      "lx": 14688.76,
      "ex": 4.33
    },
    {
      "age": 88,
      "qx": 0.175685,
      "lx": 12293.45,
      "ex": 4.07
    },
    {
      "age": 89,
      "qx": 0.188923,
      "lx": 10133.68,
      "ex": 3.84
    },
    {
      "age": 90,
      "qx": 0.202762,
      "lx": 8219.2,
      "ex": 3.61
    },
    {
      "age": 91,
      "qx": 0.21717,
      "lx": 6552.66,
      "ex": 3.4
    },
    {
      "age": 92,
      "qx": 0.232106,
      "lx": 5129.62,
      "ex": 3.21
    },
    {
      "age": 93,
      "qx": 0.247521,
      "lx": 3939.01,
      "ex": 3.03
    },
    {
      "age": 94,
      "qx": 0.263356,
      "lx": 2964.02,
      "ex": 2.86
    },
    {
      "age": 95,
      "qx": 0.279485,
      "lx": 2183.43,
      "ex": 2.71
    },
    {
      "age": 96,
      "qx": 0.295869,
      "lx": 1573.19,
      "ex": 2.56
    },
    {
      "age": 97,
      "qx": 0.312439,
      "lx": 1107.73,
      "ex": 2.43
    },
    {
      "age": 98,
      "qx": 0.329114,
      "lx": 761.63,
      "ex": 2.31
    },
    {
      "age": 99,
      "qx": 0.34581,
      "lx": 510.97,
      "ex": 2.19
    },
    {
      "age": 100,
      "qx": 1,
      "lx": 334.27,
      "ex": 2.09
    }
  ]
}