{
  "country": "THA",
  "countryName": "Thailand",
  "sex": "male",
  "year": 2023,
  "source": "UN World Population Prospects 2024",
  "sourceUrl": "https://population.un.org/wpp/",
  "downloadDate": "2025-11-14",
  "entries": [
    {
      "age": 0,
      "qx": 0.006884,
      "lx": 100000.0,
      "ex": 72.16
    },
    {
      "age": 1,
      "qx": 0.000572,
      "lx": 99311.65,
      "ex": 71.66
    },
    {
      "age": 2,
      "qx": 0.000543,
      "lx": 99254.88,
      "ex": 70.7
    },
    {
      "age": 3,
      "qx": 0.000493,
      "lx": 99200.96,
      "ex": 69.74
    },
    {
      "age": 4,
      "qx": 0.000443,
      "lx": 99152.06,
      "ex": 68.77
    },
    {
      "age": 5,
      "qx": 0.000401,
      "lx": 99108.16,
      "ex": 67.8
    },
    {
      "age": 6,
      "qx": 0.000374,
      "lx": 99068.38,
      "ex": 66.83
    },
    {
      "age": 7,
      "qx": 0.000364,
      "lx": 99031.37,
      "ex": 65.86
    },
    {
      "age": 8,
      "qx": 0.000376,
      "lx": 98995.34,
      "ex": 64.88
    },
    {
      "age": 9,
      "qx": 0.000408,
      "lx": 98958.15,
      "ex": 63.9
    },
    {
      "age": 10,
      "qx": 0.000462,
      "lx": 98917.74,
      "ex": 62.93
    },
    {
      "age": 11,
      "qx": 0.000544,
      "lx": 98872.07,
      "ex": 61.96
    },
    {
      "age": 12,
      "qx": 0.00066,
      "lx": 98818.33,
      "ex": 60.99
    },
    {
      "age": 13,
      "qx": 0.000836,
      "lx": 98753.1,
      "ex": 60.03
    },
    {
      "age": 14,
      "qx": 0.00108,
      "lx": 98670.54,
      "ex": 59.08
    },
    {
      "age": 15,
      "qx": 0.001367,
      "lx": 98564.0,
      "ex": 58.14
    },
    {
      "age": 16,
      "qx": 0.001649,
      "lx": 98429.3,
      "ex": 57.22
    },
    {
      "age": 17,
      "qx": 0.001862,
      "lx": 98266.94,
      "ex": 56.32
    },
    {
      "age": 18,
      "qx": 0.00197,
      "lx": 98084.02,
      "ex": 55.42
    },
    {
      "age": 19,
      "qx": 0.001977,
      "lx": 97890.82,
      "ex": 54.53
    },
    {
      "age": 20,
      "qx": 0.001918,
      "lx": 97697.25,
      "ex": 53.64
    },
    {
      "age": 21,
      "qx": 0.001838,
      "lx": 97509.82,
      "ex": 52.74
    },
    {
      "age": 22,
      "qx": 0.001775,
      "lx": 97330.56,
      "ex": 51.84
    },
    {
      "age": 23,
      "qx": 0.001752,
      "lx": 97157.79,
      "ex": 50.93
    },
    {
      "age": 24,
      "qx": 0.001768,
      "lx": 96987.6,
      "ex": 50.01
    },
    {
      "age": 25,
      "qx": 0.001822,
      "lx": 96816.1,
      "ex": 49.1
    },
    {
      "age": 26,
      "qx": 0.001901,
      "lx": 96639.68,
      "ex": 48.19
    },
    {
      "age": 27,
      "qx": 0.001991,
      "lx": 96455.92,
      "ex": 47.28
    },
    {
      "age": 28,
      "qx": 0.00208,
      "lx": 96263.92,
      "ex": 46.38
    },
    {
      "age": 29,
      "qx": 0.002165,
      "lx": 96063.65,
      "ex": 45.47
    },
    {
      "age": 30,
      "qx": 0.002249,
      "lx": 95855.68,
      "ex": 44.57
    },
    {
      "age": 31,
      "qx": 0.002345,
      "lx": 95640.06,
      "ex": 43.67
    },
    {
      "age": 32,
      "qx": 0.002466,
      "lx": 95415.75,
      "ex": 42.77
    },
    {
      "age": 33,
      "qx": 0.002646,
      "lx": 95180.5,
      "ex": 41.87
    },
    {
      "age": 34,
      "qx": 0.002912,
      "lx": 94928.62,
      "ex": 40.98
    },
    {
      "age": 35,
      "qx": 0.003259,
      "lx": 94652.23,
      "ex": 40.1
    },
    {
      "age": 36,
      "qx": 0.00368,
      "lx": 94343.8,
      "ex": 39.23
    },
    {
      "age": 37,
      "qx": 0.004164,
      "lx": 93996.64,
      "ex": 38.37
    },
    {
      "age": 38,
      "qx": 0.004717,
      "lx": 93605.28,
      "ex": 37.53
    },
    {
      "age": 39,
      "qx": 0.005341,
      "lx": 93163.7,
      "ex": 36.71
    },
    {
      "age": 40,
      "qx": 0.006004,
      "lx": 92666.07,
      "ex": 35.9
    },
    {
      "age": 41,
      "qx": 0.006665,
      "lx": 92109.71,
      "ex": 35.12
    },
    {
      "age": 42,
      "qx": 0.007286,
      "lx": 91495.77,
      "ex": 34.35
    },
    {
      "age": 43,
      "qx": 0.007859,
      "lx": 90829.1,
      "ex": 33.6
    },
    {
      "age": 44,
      "qx": 0.008382,
      "lx": 90115.27,
      "ex": 32.86
    },
    {
      "age": 45,
      "qx": 0.008833,
      "lx": 89359.9,
      "ex": 32.13
    },
    {
      "age": 46,
      "qx": 0.009203,
      "lx": 88570.55,
      "ex": 31.42
    },
    {
      "age": 47,
      "qx": 0.009489,
      "lx": 87755.45,
      "ex": 30.7
    },
    {
      "age": 48,
      "qx": 0.009689,
      "lx": 86922.74,
      "ex": 29.99
    },
    {
      "age": 49,
      "qx": 0.009836,
      "lx": 86080.55,
      "ex": 29.28
    },
    {
      "age": 50,
      "qx": 0.009971,
      "lx": 85233.85,
      "ex": 28.57
    },
    {
      "age": 51,
      "qx": 0.010128,
      "lx": 84383.98,
      "ex": 27.85
    },
    {
      "age": 52,
      "qx": 0.010339,
      "lx": 83529.31,
      "ex": 27.13
    },
    {
      "age": 53,
      "qx": 0.010602,
      "lx": 82665.72,
      "ex": 26.41
    },
    {
      "age": 54,
      "qx": 0.010884,
      "lx": 81789.33,
      "ex": 25.68
    },
    {
      "age": 55,
      "qx": 0.011314,
      "lx": 80899.14,
      "ex": 24.96
    },
    {
      "age": 56,
      "qx": 0.011759,
      "lx": 79983.86,
      "ex": 24.24
    },
    {
      "age": 57,
      "qx": 0.012207,
      "lx": 79043.36,
      "ex": 23.52
    },
    {
      "age": 58,
      "qx": 0.012594,
      "lx": 78078.47,
      "ex": 22.81
    },
    {
      "age": 59,
      "qx": 0.012916,
      "lx": 77095.12,
      "ex": 22.09
    },
    {
      "age": 60,
      "qx": 0.013251,
      "lx": 76099.35,
      "ex": 21.38
    },
    {
      "age": 61,
      "qx": 0.013678,
      "lx": 75090.95,
      "ex": 20.66
    },
    {
      "age": 62,
      "qx": 0.014276,
      "lx": 74063.85,
      "ex": 19.94
    },
    {
      "age": 63,
      "qx": 0.015002,
      "lx": 73006.55,
      "ex": 19.22
    },
    {
      "age": 64,
      "qx": 0.015766,
      "lx": 71911.27,
      "ex": 18.5
    },
    {
      "age": 65,
      "qx": 0.016568,
      "lx": 70777.5,
      "ex": 17.79
    },
    {
      "age": 66,
      "qx": 0.017411,
      "lx": 69604.84,
      "ex": 17.08
    },
    {
      "age": 67,
      "qx": 0.01963,
      "lx": 68392.95,
      "ex": 16.38
    },
    {
      "age": 68,
      "qx": 0.021932,
      "lx": 67050.42,
      "ex": 15.69
    },
    {
      "age": 69,
      "qx": 0.024201,
      "lx": 65579.89,
      "ex": 15.03
    },
    {
      "age": 70,
      "qx": 0.026348,
      "lx": 63992.82,
      "ex": 14.39
    },
    {
      "age": 71,
      "qx": 0.028466,
      "lx": 62306.75,
      "ex": 13.77
    },
    {
      "age": 72,
      "qx": 0.030685,
      "lx": 60533.1,
      "ex": 13.16
    },
    {
      "age": 73,
      "qx": 0.033246,
      "lx": 58675.66,
      "ex": 12.56
    },
    {
      "age": 74,
      "qx": 0.036316,
      "lx": 56724.92,
      "ex": 11.97
    },
    {
      "age": 75,
      "qx": 0.039847,
      "lx": 54664.91,
      "ex": 11.41
    },
    {
      "age": 76,
      "qx": 0.04375,
      "lx": 52486.69,
      "ex": 10.86
    },
    {
      "age": 77,
      "qx": 0.047869,
      "lx": 50190.4,
      "ex": 10.33
    },
    {
      "age": 78,
      "qx": 0.052142,
      "lx": 47787.85,
      "ex": 9.83
    },
    {
      "age": 79,
      "qx": 0.056608,
      "lx": 45296.11,
      "ex": 9.34
    },
    {
      "age": 80,
      "qx": 0.061274,
      "lx": 42731.98,
      "ex": 8.87
    },
    {
      "age": 81,
      "qx": 0.066208,
      "lx": 40113.61,
      "ex": 8.42
    },
    {
      "age": 82,
      "qx": 0.071495,
      "lx": 37457.79,
      "ex": 7.98
    },
    {
      "age": 83,
      "qx": 0.077126,
      "lx": 34779.73,
      "ex": 7.56
    },
    {
      "age": 84,
      "qx": 0.083155,
      "lx": 32097.29,
      "ex": 7.14
    },
    {
      "age": 85,
      "qx": 0.08976,
      "lx": 29428.26,
      "ex": 6.75
    },
    {
      "age": 86,
      "qx": 0.097114,
      "lx": 26786.77,
      "ex": 6.36
    },
    {
      "age": 87,
      "qx": 0.105363,
      "lx": 24185.4,
      "ex": 5.99
    },
    {
      "age": 88,
      "qx": 0.114459,
      "lx": 21637.16,
      "ex": 5.64
    },
    {
      "age": 89,
      "qx": 0.124253,
      "lx": 19160.6,
      "ex": 5.31
    },
    {
      "age": 90,
      "qx": 0.134707,
      "lx": 16779.84,
      "ex": 4.99
    },
    {
      "age": 91,
      "qx": 0.145745,
      "lx": 14519.48,
      "ex": 4.69
    },
    {
      "age": 92,
      "qx": 0.157263,
      "lx": 12403.34,
      "ex": 4.4
    },
    {
      "age": 93,
      "qx": 0.169144,
      "lx": 10452.75,
      "ex": 4.13
    },
    {
      "age": 94,
      "qx": 0.181254,
      "lx": 8684.73,
      "ex": 3.87
    },
    {
      "age": 95,
      "qx": 0.196804,
      "lx": 7110.58,
      "ex": 3.61
    },
    {
      "age": 96,
      "qx": 0.212378,
      "lx": 5711.19,
      "ex": 3.38
    },
    {
      "age": 97,
      "qx": 0.229058,
      "lx": 4498.26,
      "ex": 3.15
    },
    {
      "age": 98,
      "qx": 0.246897,
      "lx": 3467.9,
      "ex": 2.94
    },
    {
      "age": 99,
      "qx": 0.265946,
      "lx": 2611.68,
      "ex": 2.74
    },
    {
      "age": 100,
      "qx": 1.0,
      "lx": 1917.12,
      "ex": 2.55
    }
  ]
}